turbinia_api_lib/__init__.py
turbinia_api_lib/api/__init__.py
turbinia_api_lib/api/turbinia_configuration_api.py
turbinia_api_lib/api/turbinia_evidence_api.py
turbinia_api_lib/api/turbinia_jobs_api.py
turbinia_api_lib/api/turbinia_logs_api.py
turbinia_api_lib/api/turbinia_request_results_api.py
turbinia_api_lib/api/turbinia_requests_api.py
turbinia_api_lib/api/turbinia_tasks_api.py
turbinia_api_lib/api_client.py
turbinia_api_lib/api_response.py
turbinia_api_lib/configuration.py
turbinia_api_lib/exceptions.py
turbinia_api_lib/models/__init__.py
turbinia_api_lib/models/base_request_options.py
turbinia_api_lib/models/complete_turbinia_stats.py
turbinia_api_lib/models/http_validation_error.py
turbinia_api_lib/models/location_inner.py
turbinia_api_lib/models/request.py
turbinia_api_lib/models/validation_error.py
turbinia_api_lib/py.typed
turbinia_api_lib/rest.py
turbinia_api_lib-1.0.6.dist-info/LICENSE
turbinia_api_lib-1.0.6.dist-info/METADATA
turbinia_api_lib-1.0.6.dist-info/WHEEL
turbinia_api_lib-1.0.6.dist-info/RECORD
