Metadata-Version: 2.1
Name: turbinia-api-lib
Version: 1.0.6
Summary: Turbinia API Server
Home-page: https://github.com/google/turbinia
License: Apache-2.0
Keywords: OpenAPI,OpenAPI-Generator,Turbinia API Server
Author: OpenAPI Generator Community
Author-email: team@openapitools.org
Requires-Python: >=3.9,<4.0
Classifier: License :: OSI Approved :: Apache Software License
Classifier: Programming Language :: Python :: 3
Classifier: Programming Language :: Python :: 3.9
Classifier: Programming Language :: Python :: 3.10
Classifier: Programming Language :: Python :: 3.11
Classifier: Programming Language :: Python :: 3.12
Requires-Dist: aenum (>=3.1.11)
Requires-Dist: pydantic (>=1.10.5,<2.0.0)
Requires-Dist: python-dateutil (>=2.8.2)
Requires-Dist: urllib3 (>=1.25.4,<1.27) ; python_version < "3.10"
Requires-Dist: urllib3 (>=1.25.4,<2.1) ; python_version >= "3.10"
Project-URL: Repository, https://github.com/google/turbinia
